{"$type":"AQTSim","AQTSeg":{"$type":"AQUATOXSegment","Location":{"$type":"TAQTSite","Locale":{"$type":"SiteRecord","SiteName":{"$type":"TStringParam","Val":"Default Stream","Comment":""},"SiteLength":{"$type":"TParameter","Val":5.0,"Comment":""},"Volume":{"$type":"TParameter","Val":0.0,"Comment":""},"SurfArea":{"$type":"TParameter","Val":170000.0,"Comment":""},"ICZMean":{"$type":"TParameter","Val":0.82,"Comment":""},"ZMax":{"$type":"TParameter","Val":1.82,"Comment":""},"TempMean":{"$type":"TParameter","Val":13.0,"Comment":""},"TempRange":{"$type":"TParameter","Val":24.0,"Comment":""},"Latitude":{"$type":"TParameter","Val":43.57,"Comment":""},"Altitude":{"$type":"TParameter","Val":200.0,"Comment":""},"LightMean":{"$type":"TParameter","Val":258.0,"Comment":"sol.crest.org/cgi-bin/solrad/ kwhr*86 = Ly/d"},"LightRange":{"$type":"TParameter","Val":387.0,"Comment":"calc. from sol.crest; ave * 0.75 (canopy)"},"EnclWallArea":{"$type":"TParameter","Val":0.0,"Comment":"NA"},"MeanEvap":{"$type":"TParameter","Val":0.0,"Comment":""},"ECoeffWater":{"$type":"TParameter","Val":0.05,"Comment":""},"ECoeffSed":{"$type":"TParameter","Val":0.17,"Comment":"mid value from Straskraba & Gnauck, 1985"},"ECoeffDOM":{"$type":"TParameter","Val":0.03,"Comment":"calc. from Effler et al., 1985"},"ECoeffPOM":{"$type":"TParameter","Val":0.12,"Comment":"Verduin, 1982"},"BasePercentEmbed":{"$type":"TParameter","Val":0.0,"Comment":"Default, Used for O2Sat"},"Min_Vol_Frac":{"$type":"TParameter","Val":0.01,"Comment":"default"},"UseCovar":{"$type":"TBoolParam","Val":true,"Comment":""},"EnteredKReaer":{"$type":"TParameter","Val":0.0,"Comment":"NA"},"EnterTotalLength":{"$type":"TBoolParam","Val":true,"Comment":""},"TotalLength":{"$type":"TParameter","Val":40.0,"Comment":"Lucky Peak Dam is 16 km upstream"},"WaterShedArea":{"$type":"TParameter","Val":3522.0,"Comment":"SITE SUMMARY.xls mi2 converted to km2"},"FractalD":{"$type":"TParameter","Val":1.0,"Comment":"default"},"FD_Refuge_Coeff":{"$type":"TParameter","Val":-0.15,"Comment":"default"},"HalfSatOysterRefuge":{"$type":"TParameter","Val":80.0,"Comment":"default"},"Channel_Slope":{"$type":"TParameter","Val":0.002473,"Comment":""},"UseBathymetry":{"$type":"TBoolParam","Val":true,"Comment":""},"StreamType":{"$type":"TDropDownParam","Val":"Natural Channel","ValList":null,"Comment":""},"UseEnteredManning":{"$type":"TBoolParam","Val":true,"Comment":""},"EnteredManning":{"$type":"TParameter","Val":0.07,"Comment":""},"PctRiffle":{"$type":"TParameter","Val":80.0,"Comment":""},"PctPool":{"$type":"TParameter","Val":0.0,"Comment":""},"UsePhytoRetention":{"$type":"TBoolParam","Val":true,"Comment":""}},"Remin":{"$type":"ReminRecord","RemRecName":{"$type":"TStringParam","Val":"Default Remin Record","Comment":""},"DecayMax_Lab":{"$type":"TParameter","Val":0.0159,"Comment":"Gunnison 1985, p. 63 (phytoplankton)"},"DecayMax_Refr":{"$type":"TParameter","Val":0.04,"Comment":"default"},"TOpt":{"$type":"TParameter","Val":25.0,"Comment":"temperature at which degradation measured"},"TMax":{"$type":"TParameter","Val":65.0,"Comment":" Alexander, 1961"},"pHMin":{"$type":"TParameter","Val":5.0,"Comment":"Lyman et al.'82;Francis et al. in Hendrey '84"},"pHMax":{"$type":"TParameter","Val":8.5,"Comment":"Lyman et al., '82"},"KNitri":{"$type":"TParameter","Val":0.3,"Comment":"Default"},"KDenitri_Wat":{"$type":"TParameter","Val":0.09,"Comment":"Default"},"P2OrgLab":{"$type":"TParameter","Val":0.018,"Comment":"Redfield '58 ratio"},"N2OrgLab":{"$type":"TParameter","Val":0.079,"Comment":"   '"},"P2OrgRefr":{"$type":"TParameter","Val":0.0002,"Comment":"default"},"N2OrgRefr":{"$type":"TParameter","Val":0.002,"Comment":"default"},"P2OrgDissLab":{"$type":"TParameter","Val":0.0002,"Comment":"default"},"N2OrgDissLab":{"$type":"TParameter","Val":0.002,"Comment":"default"},"P2OrgDissRefr":{"$type":"TParameter","Val":0.0002,"Comment":"default"},"N2OrgDissRefr":{"$type":"TParameter","Val":0.002,"Comment":"default"},"O2Biomass":{"$type":"TParameter","Val":0.575,"Comment":"Winfield et al., '71 & Redfield '58"},"O2N":{"$type":"TParameter","Val":4.57,"Comment":"Scavia '80"},"KSed":{"$type":"TParameter","Val":0.15,"Comment":"Collins & Wlosinski '83 (0.69)"},"KSedTemp":{"$type":"TParameter","Val":0.0,"Comment":"placeholder"},"KSedSalinity":{"$type":"TParameter","Val":0.0,"Comment":"placeholder"},"PSedRelease":{"$type":"TParameter","Val":0.0,"Comment":""},"NSedRelease":{"$type":"TParameter","Val":0.0,"Comment":""},"Wet2DrySLab":{"$type":"TParameter","Val":5.0,"Comment":"<--- default"},"Wet2DrySRefr":{"$type":"TParameter","Val":5.0,"Comment":"<--- default"},"Wet2DryPLab":{"$type":"TParameter","Val":5.0,"Comment":"<--- default"},"Wet2DryPRefr":{"$type":"TParameter","Val":5.0,"Comment":"<--- default"},"KD_P_Calcite":{"$type":"TParameter","Val":300.0,"Comment":"Default"}},"SiteType":1},"SV":[{"$type":"TNH4Obj","Assimilation_Link":null,"Animal_Remin_Link":null,"Plant_Remin_Link":null,"OM_Remin_Link":null,"InitialCond":0.04,"State":0.0,"NState":20,"SVType":0,"Layer":0,"PName":"Total Ammonia as N","SVoutput":null,"LoadsRec":{"$type":"LoadingsRecord","Loadings":{"$type":"TLoadings","list":{"$type":"SortedList`2"},"Hourly":false,"ConstLoad":0.045,"UseConstant":true,"NoUserLoad":false,"MultLdg":1.0,"ExternalLink":false,"ExternalFile":"","ITSI":null},"Alt_Loadings":[{"$type":"TLoadings","list":{"$type":"SortedList`2"},"Hourly":false,"ConstLoad":0.0,"UseConstant":true,"NoUserLoad":false,"MultLdg":1.0,"ExternalLink":false,"ExternalFile":"","ITSI":null},{"$type":"TLoadings","list":{"$type":"SortedList`2"},"Hourly":false,"ConstLoad":0.0,"UseConstant":true,"NoUserLoad":false,"MultLdg":1.0,"ExternalLink":false,"ExternalFile":"","ITSI":null},{"$type":"TLoadings","list":{"$type":"SortedList`2"},"Hourly":false,"ConstLoad":0.0,"UseConstant":true,"NoUserLoad":false,"MultLdg":1.0,"ExternalLink":false,"ExternalFile":"","ITSI":null}]},"UseLoadsRecAsDriver":false,"StateUnit":"mg/L","LoadingUnit":"mg/L","SaveRates":true,"LoadNotes1":"","LoadNotes2":"","TrackResults":true},{"$type":"TNO3Obj","TN_IC":false,"TN_Inflow":false,"TN_PS":false,"TN_NPS":false,"Assimilation_Link":null,"InitialCond":0.01,"State":0.0,"NState":21,"SVType":0,"Layer":0,"PName":"Nitrate as N","SVoutput":null,"LoadsRec":{"$type":"LoadingsRecord","Loadings":{"$type":"TLoadings","list":{"$type":"SortedList`2"},"Hourly":false,"ConstLoad":0.222,"UseConstant":true,"NoUserLoad":false,"MultLdg":1.0,"ExternalLink":false,"ExternalFile":"","ITSI":null},"Alt_Loadings":[{"$type":"TLoadings","list":{"$type":"SortedList`2"},"Hourly":false,"ConstLoad":0.0,"UseConstant":true,"NoUserLoad":false,"MultLdg":1.0,"ExternalLink":false,"ExternalFile":"","ITSI":null},{"$type":"TLoadings","list":{"$type":"SortedList`2"},"Hourly":false,"ConstLoad":0.0,"UseConstant":true,"NoUserLoad":false,"MultLdg":1.0,"ExternalLink":false,"ExternalFile":"","ITSI":null},{"$type":"TLoadings","list":{"$type":"SortedList`2"},"Hourly":false,"ConstLoad":0.0,"UseConstant":true,"NoUserLoad":false,"MultLdg":1.0,"ExternalLink":false,"ExternalFile":"","ITSI":null}]},"UseLoadsRecAsDriver":false,"StateUnit":"mg/L","LoadingUnit":"mg/L","SaveRates":true,"LoadNotes1":"","LoadNotes2":"","TrackResults":true},{"$type":"TPO4Obj","FracAvail":1.0,"Alt_FracAvail":[1.0,1.0,1.0],"TP_IC":false,"TP_Inflow":false,"TP_PS":false,"TP_NPS":false,"Assimilation_Link":null,"Animal_Remin_Link":null,"Plant_Remin_Link":null,"OM_Remin_Link":null,"CalcitePcpt_Link":null,"InitialCond":0.04,"State":0.0,"NState":22,"SVType":0,"Layer":0,"PName":"Total Soluble P","SVoutput":null,"LoadsRec":{"$type":"LoadingsRecord","Loadings":{"$type":"TLoadings","list":{"$type":"SortedList`2"},"Hourly":false,"ConstLoad":0.08,"UseConstant":true,"NoUserLoad":false,"MultLdg":1.0,"ExternalLink":false,"ExternalFile":"","ITSI":null},"Alt_Loadings":[{"$type":"TLoadings","list":{"$type":"SortedList`2"},"Hourly":false,"ConstLoad":0.0,"UseConstant":true,"NoUserLoad":false,"MultLdg":1.0,"ExternalLink":false,"ExternalFile":"","ITSI":null},{"$type":"TLoadings","list":{"$type":"SortedList`2"},"Hourly":false,"ConstLoad":0.0,"UseConstant":true,"NoUserLoad":false,"MultLdg":1.0,"ExternalLink":false,"ExternalFile":"","ITSI":null},{"$type":"TLoadings","list":{"$type":"SortedList`2"},"Hourly":false,"ConstLoad":0.0,"UseConstant":true,"NoUserLoad":false,"MultLdg":1.0,"ExternalLink":false,"ExternalFile":"","ITSI":null}]},"UseLoadsRecAsDriver":false,"StateUnit":"mg/L","LoadingUnit":"mg/L","SaveRates":true,"LoadNotes1":"","LoadNotes2":"","TrackResults":true},{"$type":"TCO2Obj","ImportCo2Equil":false,"CO2Equil":{"$type":"TLoadings","list":{"$type":"SortedList`2"},"Hourly":false,"ConstLoad":0.0,"UseConstant":true,"NoUserLoad":false,"MultLdg":1.0,"ExternalLink":false,"ExternalFile":"","ITSI":null},"Assimilation_Link":null,"Respiration_Link":null,"OM_Decomp_Link":null,"InitialCond":0.7,"State":0.0,"NState":23,"SVType":0,"Layer":0,"PName":"Carbon dioxide","SVoutput":null,"LoadsRec":{"$type":"LoadingsRecord","Loadings":{"$type":"TLoadings","list":{"$type":"SortedList`2"},"Hourly":false,"ConstLoad":0.7,"UseConstant":true,"NoUserLoad":false,"MultLdg":1.0,"ExternalLink":false,"ExternalFile":"","ITSI":null},"Alt_Loadings":[{"$type":"TLoadings","list":{"$type":"SortedList`2"},"Hourly":false,"ConstLoad":0.0,"UseConstant":true,"NoUserLoad":false,"MultLdg":1.0,"ExternalLink":false,"ExternalFile":"","ITSI":null},{"$type":"TLoadings","list":{"$type":"SortedList`2"},"Hourly":false,"ConstLoad":0.0,"UseConstant":true,"NoUserLoad":false,"MultLdg":1.0,"ExternalLink":false,"ExternalFile":"","ITSI":null},{"$type":"TLoadings","list":{"$type":"SortedList`2"},"Hourly":false,"ConstLoad":0.0,"UseConstant":true,"NoUserLoad":false,"MultLdg":1.0,"ExternalLink":false,"ExternalFile":"","ITSI":null}]},"UseLoadsRecAsDriver":false,"StateUnit":"mg/L","LoadingUnit":"mg/L","SaveRates":true,"LoadNotes1":"","LoadNotes2":"","TrackResults":true},{"$type":"TO2Obj","NoLoadOrWash":false,"Photosynthesis_Link":null,"Respiration_Link":null,"Nitrification_Link":null,"CBOD_Link":null,"SOD_Link":null,"InitialCond":9.68,"State":0.0,"NState":24,"SVType":0,"Layer":0,"PName":"Oxygen","SVoutput":null,"LoadsRec":{"$type":"LoadingsRecord","Loadings":{"$type":"TLoadings","list":{"$type":"SortedList`2"},"Hourly":false,"ConstLoad":6.6003,"UseConstant":true,"NoUserLoad":false,"MultLdg":1.0,"ExternalLink":false,"ExternalFile":"","ITSI":null},"Alt_Loadings":[{"$type":"TLoadings","list":{"$type":"SortedList`2"},"Hourly":false,"ConstLoad":0.0,"UseConstant":true,"NoUserLoad":false,"MultLdg":1.0,"ExternalLink":false,"ExternalFile":"","ITSI":null},{"$type":"TLoadings","list":{"$type":"SortedList`2"},"Hourly":false,"ConstLoad":0.0,"UseConstant":true,"NoUserLoad":false,"MultLdg":1.0,"ExternalLink":false,"ExternalFile":"","ITSI":null},{"$type":"TLoadings","list":{"$type":"SortedList`2"},"Hourly":false,"ConstLoad":0.0,"UseConstant":true,"NoUserLoad":false,"MultLdg":1.0,"ExternalLink":false,"ExternalFile":"","ITSI":null}]},"UseLoadsRecAsDriver":false,"StateUnit":"mg/L","LoadingUnit":"mg/L","SaveRates":true,"LoadNotes1":"","LoadNotes2":"","TrackResults":true},{"$type":"TSedRefrDetr","Predation_Link":null,"DF_Mort_Link":null,"DF_Excr_Link":null,"DF_Sed_Link":null,"DF_Gameteloss_Link":null,"InitialCond":1.0,"State":0.0,"NState":51,"SVType":0,"Layer":0,"PName":"Refrac. sed. detritus","SVoutput":null,"LoadsRec":{"$type":"LoadingsRecord","Loadings":{"$type":"TLoadings","list":{"$type":"SortedList`2"},"Hourly":false,"ConstLoad":0.001,"UseConstant":true,"NoUserLoad":false,"MultLdg":1.0,"ExternalLink":false,"ExternalFile":"","ITSI":null},"Alt_Loadings":[{"$type":"TLoadings","list":{"$type":"SortedList`2"},"Hourly":false,"ConstLoad":0.0,"UseConstant":true,"NoUserLoad":false,"MultLdg":1.0,"ExternalLink":false,"ExternalFile":"","ITSI":null},{"$type":"TLoadings","list":{"$type":"SortedList`2"},"Hourly":false,"ConstLoad":0.0,"UseConstant":true,"NoUserLoad":false,"MultLdg":1.0,"ExternalLink":false,"ExternalFile":"","ITSI":null},{"$type":"TLoadings","list":{"$type":"SortedList`2"},"Hourly":false,"ConstLoad":0.0,"UseConstant":true,"NoUserLoad":false,"MultLdg":1.0,"ExternalLink":false,"ExternalFile":"","ITSI":null}]},"UseLoadsRecAsDriver":false,"StateUnit":"g/m2 dry","LoadingUnit":"N A","SaveRates":true,"LoadNotes1":"","LoadNotes2":"","TrackResults":true},{"$type":"TSedLabileDetr","Predation_Link":null,"DF_Mort_Link":null,"DF_Excr_Link":null,"DF_Sed_Link":null,"DF_Gameteloss_Link":null,"InitialCond":0.5,"State":0.0,"NState":52,"SVType":0,"Layer":0,"PName":"Labile sed. detritus","SVoutput":null,"LoadsRec":{"$type":"LoadingsRecord","Loadings":{"$type":"TLoadings","list":{"$type":"SortedList`2"},"Hourly":false,"ConstLoad":0.001,"UseConstant":true,"NoUserLoad":false,"MultLdg":1.0,"ExternalLink":false,"ExternalFile":"","ITSI":null},"Alt_Loadings":[{"$type":"TLoadings","list":{"$type":"SortedList`2"},"Hourly":false,"ConstLoad":0.0,"UseConstant":true,"NoUserLoad":false,"MultLdg":1.0,"ExternalLink":false,"ExternalFile":"","ITSI":null},{"$type":"TLoadings","list":{"$type":"SortedList`2"},"Hourly":false,"ConstLoad":0.0,"UseConstant":true,"NoUserLoad":false,"MultLdg":1.0,"ExternalLink":false,"ExternalFile":"","ITSI":null},{"$type":"TLoadings","list":{"$type":"SortedList`2"},"Hourly":false,"ConstLoad":0.0,"UseConstant":true,"NoUserLoad":false,"MultLdg":1.0,"ExternalLink":false,"ExternalFile":"","ITSI":null}]},"UseLoadsRecAsDriver":false,"StateUnit":"g/m2 dry","LoadingUnit":"N A","SaveRates":true,"LoadNotes1":"","LoadNotes2":"","TrackResults":true},{"$type":"TDissRefrDetr","InputRecord":{"$type":"DetritalInputRecordType","DataType":0,"InitCond":5.0,"Percent_PartIC":18.5243509,"Percent_RefrIC":60.0,"Load":{"$type":"LoadingsRecord","Loadings":{"$type":"TLoadings","list":{"$type":"SortedList`2"},"Hourly":false,"ConstLoad":5.0,"UseConstant":true,"NoUserLoad":false,"MultLdg":1.0,"ExternalLink":false,"ExternalFile":"","ITSI":null},"Alt_Loadings":[{"$type":"TLoadings","list":{"$type":"SortedList`2"},"Hourly":false,"ConstLoad":0.0,"UseConstant":true,"NoUserLoad":false,"MultLdg":1.0,"ExternalLink":false,"ExternalFile":"","ITSI":null},{"$type":"TLoadings","list":{"$type":"SortedList`2"},"Hourly":false,"ConstLoad":0.0,"UseConstant":true,"NoUserLoad":false,"MultLdg":1.0,"ExternalLink":false,"ExternalFile":"","ITSI":null},{"$type":"TLoadings","list":{"$type":"SortedList`2"},"Hourly":false,"ConstLoad":0.0,"UseConstant":true,"NoUserLoad":false,"MultLdg":1.0,"ExternalLink":false,"ExternalFile":"","ITSI":null}]},"Percent_Part":{"$type":"LoadingsRecord","Loadings":{"$type":"TLoadings","list":{"$type":"SortedList`2"},"Hourly":false,"ConstLoad":5.74,"UseConstant":true,"NoUserLoad":false,"MultLdg":1.0,"ExternalLink":false,"ExternalFile":"","ITSI":null},"Alt_Loadings":[{"$type":"TLoadings","list":{"$type":"SortedList`2"},"Hourly":false,"ConstLoad":5.74,"UseConstant":true,"NoUserLoad":false,"MultLdg":1.0,"ExternalLink":false,"ExternalFile":"","ITSI":null},{"$type":"TLoadings","list":{"$type":"SortedList`2"},"Hourly":false,"ConstLoad":5.74,"UseConstant":true,"NoUserLoad":false,"MultLdg":1.0,"ExternalLink":false,"ExternalFile":"","ITSI":null},{"$type":"TLoadings","list":{"$type":"SortedList`2"},"Hourly":false,"ConstLoad":5.74,"UseConstant":true,"NoUserLoad":false,"MultLdg":1.0,"ExternalLink":false,"ExternalFile":"","ITSI":null}]},"Percent_Refr":{"$type":"LoadingsRecord","Loadings":{"$type":"TLoadings","list":{"$type":"SortedList`2"},"Hourly":false,"ConstLoad":60.0,"UseConstant":true,"NoUserLoad":false,"MultLdg":1.0,"ExternalLink":false,"ExternalFile":"","ITSI":null},"Alt_Loadings":[{"$type":"TLoadings","list":{"$type":"SortedList`2"},"Hourly":false,"ConstLoad":50.0,"UseConstant":true,"NoUserLoad":false,"MultLdg":1.0,"ExternalLink":false,"ExternalFile":"","ITSI":null},{"$type":"TLoadings","list":{"$type":"SortedList`2"},"Hourly":false,"ConstLoad":50.0,"UseConstant":true,"NoUserLoad":false,"MultLdg":1.0,"ExternalLink":false,"ExternalFile":"","ITSI":null},{"$type":"TLoadings","list":{"$type":"SortedList`2"},"Hourly":false,"ConstLoad":50.0,"UseConstant":true,"NoUserLoad":false,"MultLdg":1.0,"ExternalLink":false,"ExternalFile":"","ITSI":null}]},"ToxInitCond":[0.0,0.0,0.0,0.0,0.0,0.0,0.0,0.0,0.0,0.0,0.0,0.0,0.0,0.0,0.0,0.0,0.0,0.0,0.0,0.0],"ToxLoad":[null,null,null,null,null,null,null,null,null,null,null,null,null,null,null,null,null,null,null,null]},"DF_Mort_Link":null,"DF_Excr_Link":null,"DF_Sed_Link":null,"DF_Gameteloss_Link":null,"InitialCond":18.204919034904,"State":0.0,"NState":53,"SVType":0,"Layer":0,"PName":"Diss Refr Detr","SVoutput":null,"LoadsRec":{"$type":"LoadingsRecord","Loadings":{"$type":"TLoadings","list":{"$type":"SortedList`2"},"Hourly":false,"ConstLoad":10.7904135,"UseConstant":true,"NoUserLoad":false,"MultLdg":1.0,"ExternalLink":false,"ExternalFile":"","ITSI":null},"Alt_Loadings":[{"$type":"TLoadings","list":{"$type":"SortedList`2"},"Hourly":false,"ConstLoad":0.0,"UseConstant":true,"NoUserLoad":false,"MultLdg":1.0,"ExternalLink":false,"ExternalFile":"","ITSI":null},{"$type":"TLoadings","list":{"$type":"SortedList`2"},"Hourly":false,"ConstLoad":0.0,"UseConstant":true,"NoUserLoad":false,"MultLdg":1.0,"ExternalLink":false,"ExternalFile":"","ITSI":null},{"$type":"TLoadings","list":{"$type":"SortedList`2"},"Hourly":false,"ConstLoad":0.0,"UseConstant":true,"NoUserLoad":false,"MultLdg":1.0,"ExternalLink":false,"ExternalFile":"","ITSI":null}]},"UseLoadsRecAsDriver":false,"StateUnit":"mg/L dry","LoadingUnit":"mg/L dry","SaveRates":true,"LoadNotes1":"","LoadNotes2":"","TrackResults":true},{"$type":"TDissLabDetr","DF_Mort_Link":null,"DF_Excr_Link":null,"DF_Sed_Link":null,"DF_Gameteloss_Link":null,"InitialCond":12.136612689936,"State":0.0,"NState":54,"SVType":0,"Layer":0,"PName":"Diss Lab Detr","SVoutput":null,"LoadsRec":{"$type":"LoadingsRecord","Loadings":{"$type":"TLoadings","list":{"$type":"SortedList`2"},"Hourly":false,"ConstLoad":10.7904135,"UseConstant":true,"NoUserLoad":false,"MultLdg":1.0,"ExternalLink":false,"ExternalFile":"","ITSI":null},"Alt_Loadings":[{"$type":"TLoadings","list":{"$type":"SortedList`2"},"Hourly":false,"ConstLoad":0.0,"UseConstant":true,"NoUserLoad":false,"MultLdg":1.0,"ExternalLink":false,"ExternalFile":"","ITSI":null},{"$type":"TLoadings","list":{"$type":"SortedList`2"},"Hourly":false,"ConstLoad":0.0,"UseConstant":true,"NoUserLoad":false,"MultLdg":1.0,"ExternalLink":false,"ExternalFile":"","ITSI":null},{"$type":"TLoadings","list":{"$type":"SortedList`2"},"Hourly":false,"ConstLoad":0.0,"UseConstant":true,"NoUserLoad":false,"MultLdg":1.0,"ExternalLink":false,"ExternalFile":"","ITSI":null}]},"UseLoadsRecAsDriver":false,"StateUnit":"mg/L dry","LoadingUnit":"mg/L dry","SaveRates":true,"LoadNotes1":"","LoadNotes2":"","TrackResults":true},{"$type":"TSuspRefrDetr","Predation_Link":null,"DF_Mort_Link":null,"DF_Excr_Link":null,"DF_Sed_Link":null,"DF_Gameteloss_Link":null,"InitialCond":4.139080965096,"State":0.0,"NState":55,"SVType":0,"Layer":0,"PName":"Susp Refr Detr","SVoutput":null,"LoadsRec":{"$type":"LoadingsRecord","Loadings":{"$type":"TLoadings","list":{"$type":"SortedList`2"},"Hourly":false,"ConstLoad":0.6570865,"UseConstant":true,"NoUserLoad":false,"MultLdg":1.0,"ExternalLink":false,"ExternalFile":"","ITSI":null},"Alt_Loadings":[{"$type":"TLoadings","list":{"$type":"SortedList`2"},"Hourly":false,"ConstLoad":0.0,"UseConstant":true,"NoUserLoad":false,"MultLdg":1.0,"ExternalLink":false,"ExternalFile":"","ITSI":null},{"$type":"TLoadings","list":{"$type":"SortedList`2"},"Hourly":false,"ConstLoad":0.0,"UseConstant":true,"NoUserLoad":false,"MultLdg":1.0,"ExternalLink":false,"ExternalFile":"","ITSI":null},{"$type":"TLoadings","list":{"$type":"SortedList`2"},"Hourly":false,"ConstLoad":0.0,"UseConstant":true,"NoUserLoad":false,"MultLdg":1.0,"ExternalLink":false,"ExternalFile":"","ITSI":null}]},"UseLoadsRecAsDriver":false,"StateUnit":"mg/L dry","LoadingUnit":"mg/L dry","SaveRates":true,"LoadNotes1":"","LoadNotes2":"","TrackResults":true},{"$type":"TSuspLabDetr","Predation_Link":null,"DF_Mort_Link":null,"DF_Excr_Link":null,"DF_Sed_Link":null,"DF_Gameteloss_Link":null,"InitialCond":2.759387310064,"State":0.0,"NState":56,"SVType":0,"Layer":0,"PName":"Susp Lab Detr","SVoutput":null,"LoadsRec":{"$type":"LoadingsRecord","Loadings":{"$type":"TLoadings","list":{"$type":"SortedList`2"},"Hourly":false,"ConstLoad":0.6570865,"UseConstant":true,"NoUserLoad":false,"MultLdg":1.0,"ExternalLink":false,"ExternalFile":"","ITSI":null},"Alt_Loadings":[{"$type":"TLoadings","list":{"$type":"SortedList`2"},"Hourly":false,"ConstLoad":0.0,"UseConstant":true,"NoUserLoad":false,"MultLdg":1.0,"ExternalLink":false,"ExternalFile":"","ITSI":null},{"$type":"TLoadings","list":{"$type":"SortedList`2"},"Hourly":false,"ConstLoad":0.0,"UseConstant":true,"NoUserLoad":false,"MultLdg":1.0,"ExternalLink":false,"ExternalFile":"","ITSI":null},{"$type":"TLoadings","list":{"$type":"SortedList`2"},"Hourly":false,"ConstLoad":0.0,"UseConstant":true,"NoUserLoad":false,"MultLdg":1.0,"ExternalLink":false,"ExternalFile":"","ITSI":null}]},"UseLoadsRecAsDriver":false,"StateUnit":"mg/L dry","LoadingUnit":"mg/L dry","SaveRates":true,"LoadNotes1":"","LoadNotes2":"","TrackResults":true},{"$type":"TVolume","Calc_Method":0,"InitialCond":180000.0,"State":0.0,"NState":144,"SVType":0,"Layer":0,"PName":"Water Volume","SVoutput":null,"LoadsRec":{"$type":"LoadingsRecord","Loadings":{"$type":"TLoadings","list":{"$type":"SortedList`2"},"Hourly":false,"ConstLoad":0.0,"UseConstant":true,"NoUserLoad":false,"MultLdg":1.0,"ExternalLink":false,"ExternalFile":"","ITSI":null},"Alt_Loadings":[{"$type":"TLoadings","list":{"$type":"SortedList`2"},"Hourly":false,"ConstLoad":712750.0,"UseConstant":true,"NoUserLoad":false,"MultLdg":1.0,"ExternalLink":false,"ExternalFile":"","ITSI":null},{"$type":"TLoadings","list":{"$type":"SortedList`2"},"Hourly":false,"ConstLoad":600880.0,"UseConstant":true,"NoUserLoad":false,"MultLdg":1.0,"ExternalLink":false,"ExternalFile":"","ITSI":null},{"$type":"TLoadings","list":{"$type":"SortedList`2"},"Hourly":false,"ConstLoad":0.0,"UseConstant":true,"NoUserLoad":false,"MultLdg":1.0,"ExternalLink":false,"ExternalFile":"","ITSI":null}]},"UseLoadsRecAsDriver":false,"StateUnit":"cu.m","LoadingUnit":"cu.m","SaveRates":true,"LoadNotes1":"","LoadNotes2":"","TrackResults":true},{"$type":"TTemperature","InitialCond":17.0,"State":0.0,"NState":145,"SVType":0,"Layer":0,"PName":"Temperature","SVoutput":null,"LoadsRec":{"$type":"LoadingsRecord","Loadings":{"$type":"TLoadings","list":{"$type":"SortedList`2"},"Hourly":false,"ConstLoad":0.0,"UseConstant":true,"NoUserLoad":true,"MultLdg":1.0,"ExternalLink":false,"ExternalFile":"","ITSI":null},"Alt_Loadings":[{"$type":"TLoadings","list":{"$type":"SortedList`2"},"Hourly":false,"ConstLoad":0.0,"UseConstant":true,"NoUserLoad":false,"MultLdg":1.0,"ExternalLink":false,"ExternalFile":"","ITSI":null},{"$type":"TLoadings","list":{"$type":"SortedList`2"},"Hourly":false,"ConstLoad":0.0,"UseConstant":true,"NoUserLoad":false,"MultLdg":1.0,"ExternalLink":false,"ExternalFile":"","ITSI":null},{"$type":"TLoadings","list":{"$type":"SortedList`2"},"Hourly":false,"ConstLoad":0.0,"UseConstant":true,"NoUserLoad":false,"MultLdg":1.0,"ExternalLink":false,"ExternalFile":"","ITSI":null}]},"UseLoadsRecAsDriver":false,"StateUnit":"deg. C","LoadingUnit":"deg. C","SaveRates":true,"LoadNotes1":"","LoadNotes2":"","TrackResults":true},{"$type":"TpHObj","Alkalinity":1000.0,"InitialCond":8.8157,"State":0.0,"NState":148,"SVType":0,"Layer":0,"PName":"pH","SVoutput":null,"LoadsRec":{"$type":"LoadingsRecord","Loadings":{"$type":"TLoadings","list":{"$type":"SortedList`2"},"Hourly":false,"ConstLoad":8.8157,"UseConstant":true,"NoUserLoad":false,"MultLdg":1.0,"ExternalLink":false,"ExternalFile":"","ITSI":null},"Alt_Loadings":[{"$type":"TLoadings","list":{"$type":"SortedList`2"},"Hourly":false,"ConstLoad":0.0,"UseConstant":true,"NoUserLoad":false,"MultLdg":1.0,"ExternalLink":false,"ExternalFile":"","ITSI":null},{"$type":"TLoadings","list":{"$type":"SortedList`2"},"Hourly":false,"ConstLoad":0.0,"UseConstant":true,"NoUserLoad":false,"MultLdg":1.0,"ExternalLink":false,"ExternalFile":"","ITSI":null},{"$type":"TLoadings","list":{"$type":"SortedList`2"},"Hourly":false,"ConstLoad":0.0,"UseConstant":true,"NoUserLoad":false,"MultLdg":1.0,"ExternalLink":false,"ExternalFile":"","ITSI":null}]},"UseLoadsRecAsDriver":false,"StateUnit":"pH","LoadingUnit":"pH","SaveRates":true,"LoadNotes1":"","LoadNotes2":"","TrackResults":true}],"TPresent":"0001-01-01T00:00:00","StudyName":"Multi-Seg OM Base","RunID":"","FileName":"C:\\work\\AQUATOX\\HMS\\hms_backend\\GUI\\GUI.AQUATOX\\2D_Inputs\\BaseJSON\\MS_OM.json","PSetup":{"$type":"Setup_Record","FirstDay":{"$type":"TDateParam","Val":"2000-06-01T00:00:00","ValList":null,"Comment":""},"LastDay":{"$type":"TDateParam","Val":"2000-06-30T00:00:00","ValList":null,"Comment":""},"StoreStepSize":{"$type":"TParameter","Val":1.0,"Comment":""},"MinStepSize":{"$type":"TParameter","Val":1E-10,"Comment":""},"RelativeError":{"$type":"TParameter","Val":0.005,"Comment":""},"SaveBRates":{"$type":"TBoolParam","Val":true,"Comment":""},"ChemsDrivingVars":{"$type":"TBoolParam","Val":false,"Comment":""},"AverageOutput":{"$type":"TBoolParam","Val":true,"Comment":""},"UseExternalConcs":{"$type":"TBoolParam","Val":false,"Comment":""},"StepSizeInDays":{"$type":"TBoolParam","Val":false,"Comment":""},"ModelTSDays":{"$type":"TBoolParam","Val":false,"Comment":""},"NFix_UseRatio":{"$type":"TBoolParam","Val":false,"Comment":""},"NtoPRatio":{"$type":"TParameter","Val":7.0,"Comment":""},"FixStepSize":{"$type":"TParameter","Val":0.1,"Comment":""},"UseFixStepSize":{"$type":"TBoolParam","Val":false,"Comment":""},"Internal_Nutrients":{"$type":"TBoolParam","Val":false,"Comment":""},"T1IsAggregate":{"$type":"TBoolParam","Val":false,"Comment":""},"AmmoniaIsDriving":{"$type":"TBoolParam","Val":false,"Comment":""},"TSedDetrIsDriving":{"$type":"TBoolParam","Val":false,"Comment":""},"UseDetrInputRecInflow":{"$type":"TBoolParam","Val":true,"Comment":""}},"UseConstEvap":true,"DynEvap":null,"UseConstZMean":true,"DynZMean":null,"Shade":{"$type":"LoadingsRecord","Loadings":{"$type":"TLoadings","list":{"$type":"SortedList`2"},"Hourly":false,"ConstLoad":0.0,"UseConstant":true,"NoUserLoad":false,"MultLdg":1.0,"ExternalLink":false,"ExternalFile":"","ITSI":null},"Alt_Loadings":[{"$type":"TLoadings","list":{"$type":"SortedList`2"},"Hourly":false,"ConstLoad":0.0,"UseConstant":true,"NoUserLoad":false,"MultLdg":1.0,"ExternalLink":false,"ExternalFile":"","ITSI":null},{"$type":"TLoadings","list":{"$type":"SortedList`2"},"Hourly":false,"ConstLoad":0.0,"UseConstant":true,"NoUserLoad":false,"MultLdg":1.0,"ExternalLink":false,"ExternalFile":"","ITSI":null},{"$type":"TLoadings","list":{"$type":"SortedList`2"},"Hourly":false,"ConstLoad":0.0,"UseConstant":true,"NoUserLoad":false,"MultLdg":1.0,"ExternalLink":false,"ExternalFile":"","ITSI":null}]},"Graphs":{"$type":"TGraphs","SelectedGraph":0,"GList":[]},"CalcVelocity":true,"DynVelocity":null,"MeanDischarge":0.0,"Diagenesis_Params":null,"Diagenesis_Steady_State":false,"MF_Spawn_Age":3.0,"BenthicBiomass_Link":null,"AnimalDef_Link":null},"SavedRuns":{"$type":"Dictionary`2"}}